bqunit/__init__.py
bqunit/bqunit.py
bqunit/query_builder.py
bqunit/table_mapper.py
bqunit-0.1.3.dist-info/LICENSE
bqunit-0.1.3.dist-info/WHEEL
bqunit-0.1.3.dist-info/METADATA
bqunit-0.1.3.dist-info/RECORD
