Metadata-Version: 2.1
Name: bqunit
Version: 0.1.3
Summary: Testing framework for BigQuery SQL
Home-page: https://github.com/to-lz1/bqunit
License: MIT
Keywords: BigQuery,sql,test
Author: to-lz1
Author-email: m.toriyama000@gmail.com
Requires-Python: >=3.7,<4.0
Classifier: License :: OSI Approved :: MIT License
Classifier: Programming Language :: Python :: 3
Classifier: Programming Language :: Python :: 3.7
Classifier: Programming Language :: Python :: 3.8
Classifier: Topic :: Software Development :: Testing
Classifier: Topic :: Utilities
Requires-Dist: google-cloud-bigquery (>=1.24.0,<2.0.0)
Project-URL: Repository, https://github.com/to-lz1/bqunit
